checkoutbot/__init__.py
checkoutbot/core/__init__.py
checkoutbot/core/captcha_handling.py
checkoutbot/core/checkout.py
checkoutbot/core/notification.py
checkoutbot/core/proxy_management.py
checkoutbot/core/scraping.py
checkoutbot/security/__init__.py
checkoutbot/security/authentication.py
checkoutbot/security/encryption.py
checkoutbot/ui/__init__.py
checkoutbot/ui/dashboard.py
checkoutbot/ui/utils.py
checkoutbot/ui/static/css/styles.css
checkoutbot/ui/static/js/scripts.js
checkoutbot/ui/templates/base.html
checkoutbot/ui/templates/index.html
checkoutbot/ui/templates/payment.html
checkoutbot/ui/templates/scraping.html
checkoutbot/ui/templates/settings.html
checkoutbot/ui/templates/templates.html
checkout_bot-1.0.0.dist-info/LICENSE
checkout_bot-1.0.0.dist-info/METADATA
checkout_bot-1.0.0.dist-info/WHEEL
checkout_bot-1.0.0.dist-info/top_level.txt
checkout_bot-1.0.0.dist-info/RECORD
