Metadata-Version: 2.1
Name: checkout-bot
Version: 1.0.0
Summary: A comprehensive, customizable, and scalable library for creating AI-enhanced checkout bots.
Home-page: https://github.com/Farzin312/checkoutbot
Author: Farzin Shifat
Author-email: farzinshifat@gmail.com
Classifier: Programming Language :: Python :: 3
Classifier: License :: OSI Approved :: MIT License
Classifier: Operating System :: OS Independent
Requires-Python: >=3.6
License-File: LICENSE
Requires-Dist: beautifulsoup4 (==4.12.3)
Requires-Dist: requests (==2.32.3)
Requires-Dist: selenium (==4.22.0)
Requires-Dist: tensorflow (==2.16.2)
Requires-Dist: flask (==3.0.3)
Requires-Dist: jinja2 (==3.1.4)
Requires-Dist: psycopg2
Requires-Dist: paypalrestsdk (==1.13.3)
Requires-Dist: yagmail (==0.15.293)
Requires-Dist: python-dotenv (==1.0.1)
Requires-Dist: lxml (==5.2.2)
Requires-Dist: pillow (==10.4.0)
Requires-Dist: twilio (==9.2.3)
Requires-Dist: premailer (==3.10.0)
Requires-Dist: cryptography (==42.0.8)
Requires-Dist: pysocks (==1.7.1)
